or_datasets/__init__.py
or_datasets/_version.py
or_datasets/bunch.py
or_datasets/linerlib.py
or_datasets/pisinger.py
or_datasets/vrp_rep.py
or_datasets-0.0.3.dist-info/LICENSE
or_datasets-0.0.3.dist-info/METADATA
or_datasets-0.0.3.dist-info/WHEEL
or_datasets-0.0.3.dist-info/top_level.txt
or_datasets-0.0.3.dist-info/RECORD
