Metadata-Version: 2.1
Name: or-datasets
Version: 0.0.3
Summary: OR Datasets
Home-page: https://flowty.ai
Author: Flowty
Author-email: info@flowty.ai
License: UNKNOWN
Keywords: Optimization,Nework Optimization,Combinatorial Optimization,Linear Programming,Integer Programming,Operations Research,Mathematical Programming
Platform: UNKNOWN
Classifier: License :: OSI Approved :: MIT License
Classifier: Programming Language :: Python :: 3.6
Classifier: Programming Language :: Python :: 3.7
Classifier: Programming Language :: Python :: 3.8
Classifier: Programming Language :: Python :: 3.9
Requires-Python: >=3.6
